dbutils/__init__.py
dbutils/persistent_db.py
dbutils/persistent_pg.py
dbutils/pooled_db.py
dbutils/pooled_pg.py
dbutils/simple_pooled_db.py
dbutils/simple_pooled_pg.py
dbutils/steady_db.py
dbutils/steady_pg.py
DBUtils-3.0.0.dist-info/LICENSE
DBUtils-3.0.0.dist-info/METADATA
DBUtils-3.0.0.dist-info/WHEEL
DBUtils-3.0.0.dist-info/top_level.txt
DBUtils-3.0.0.dist-info/RECORD
