Metadata-Version: 2.1
Name: DBUtils
Version: 3.0.0
Summary: Database connections for multi-threaded environments.
Home-page: https://webwareforpython.github.io/DBUtils/
Author: Christoph Zwerschke
Author-email: cito@online.de
License: MIT License
Download-URL: https://pypi.org/project/DBUtils/
Project-URL: Documentation, https://webwareforpython.github.io/DBUtils/main.html
Project-URL: Changelog, https://webwareforpython.github.io/DBUtils/changelog.html
Project-URL: Issue Tracker, https://github.com/WebwareForPython/DBUtils/issues
Project-URL: Source Code, https://github.com/WebwareForPython/DBUtils
Platform: any
Classifier: Development Status :: 5 - Production/Stable
Classifier: Environment :: Web Environment
Classifier: Intended Audience :: Developers
Classifier: Topic :: Database
Classifier: Topic :: Internet :: WWW/HTTP :: Dynamic Content
Classifier: Topic :: Software Development :: Libraries :: Python Modules
Classifier: License :: OSI Approved :: MIT License
Classifier: Programming Language :: Python
Classifier: Programming Language :: Python :: 3
Classifier: Programming Language :: Python :: 3.6
Classifier: Programming Language :: Python :: 3.7
Classifier: Programming Language :: Python :: 3.8
Classifier: Programming Language :: Python :: 3.9
Classifier: Programming Language :: Python :: 3.10
Classifier: Operating System :: OS Independent
License-File: LICENSE
